merph/__init__.py
merph/__main__.py
merph/main.py
merph/data/AubryData.csv
merph/data/IVESPAData.csv
merph/data/MastinData.csv
merph/data/SparksData.csv
merph/notebooks/__init__.py
merph/notebooks/merph_example1.ipynb
merph/notebooks/merph_example2.ipynb
merph/notebooks/notebook_tools.py
merph/scripts/__init__.py
merph/scripts/example.py
merph/scripts/run_merph.py
merph/utilities/__init__.py
merph/utilities/number_tools.py
merph/utilities/plot_tools.py
merph-1.0.0.dist-info/LICENSE
merph-1.0.0.dist-info/METADATA
merph-1.0.0.dist-info/WHEEL
merph-1.0.0.dist-info/entry_points.txt
merph-1.0.0.dist-info/top_level.txt
merph-1.0.0.dist-info/RECORD
