Metadata-Version: 2.1
Name: merph
Version: 1.0.0
Summary: Bayesian methods for inferring mass eruption rate for column height (or vice versa) for volcanic eruptions
Author-email: "Mark J. Woodhouse" <mark.woodhouse@bristol.ac.uk>
License: Copyright 2024 Mark J. Woodhouse
Project-URL: Homepage, https://bitbucket.org/markwoodhouse/merph
Project-URL: Bug Tacker, https://bitbucket.org/markwoodhouse/merph/admin/issues
Classifier: Programming Language :: Python :: 3
Classifier: License :: OSI Approved :: BSD License
Classifier: Operating System :: OS Independent
Requires-Python: >=3.10
License-File: LICENSE
Requires-Dist: matplotlib >=3.7.0
Requires-Dist: numpy >=1.24.0
Requires-Dist: pandas >=1.4.1
Requires-Dist: scipy >=1.8.0
Requires-Dist: click >=4.0
Provides-Extra: nb
Requires-Dist: notebook ; extra == 'nb'
